{
  "back": "Précédent",
  "next": "Suivant",
  "skip": "Passer",
  "close": "Fermer",
  "last": "Dernier",
  "open": "Ouvrir",

  "guided-tour": "Visite guidée",
  "guided-tour-hint": "Bonjour, <br/> <bold>besoin d'aide? </bold> <br/> Suivez le guide!",

  "title-tour-start": "Bienvenue",
  "tour-start": "Démarrer la visite",

  "title-formular-side-tour-guide": "Formulaire",
  "formular-side-tour-guide": "Ceci est le formulaire à remplir avant de pouvoir dessiner. <br> Renseignez chaque champ.",
  "formular-side-tour-guide-candraw": "Le formulaire est rempli, passons au dessin",

  "title-drawer-side-tour-guide": "Dessinateur",
  "drawer-side-tour-guide": "Ceci est la zone de dessin",

  "title-cannot-draw-panel": "Renseigner le formulaire pour pouvoir dessiner",
  "cannot-draw-panel": "Renseigner le formulaire pour pouvoir dessiner",

  "title-configurator-compute": "Calculer",
  "configurator-compute": "Calculer",

  "title-configurator-drawer-2D-3D-switch": "Basculer Dessin - Visuel 2D - Visuel 3D",
  "configurator-drawer-2D-3D-switch": "Basculer Dessin - Visuel 2D - Visuel 3D",

  "title-configurator-exports": "Téléchargements",
  "configurator-exports": "Téléchargements",

  "title-crisp-chatbox-tour-guide": "Aide",
  "crisp-chatbox-tour-guide": "Besoin d'aide? Nous sommes à votre écoute.",

  "title-drawer-action-toggle-group": "Dessinateur",
  "drawer-action-toggle-group": "Dessinateur",

  "title-drawer-action-select": "Sélectionner outil",
  "drawer-action-select": "Cliquez pour vous déplacer dans le dessin ou zoomer",

  "title-drawer-action-line": "Dessin",
  "drawer-action-line": "Cliquer pour tracer des lignes, ajuster segments, les cotes et les angles",

  "title-drawer-action-undo-redo-reset": "Plus de fonctions",
  "drawer-action-line-undo-redo-reset": "Plus de fonctions",

  "title-drawer-settings": "Paramètres dessinateur",
  "drawer-settings": "Paramètres dessinateur"
}
